XMZAPI/APM.py
XMZAPI/KVS.py
XMZAPI/__init__.py
XMZSDK-0.2.0.dist-info/METADATA
XMZSDK-0.2.0.dist-info/WHEEL
XMZSDK-0.2.0.dist-info/top_level.txt
XMZSDK-0.2.0.dist-info/RECORD
