Metadata-Version: 2.1
Name: XMZSDK
Version: 0.2.0
Home-page: https://github.com/xiaomizhoubaobei/XMZAPI
Author: 小米粥
Author-email: mzapi@x.mizhoubaobei.top
Classifier: Development Status :: 3 - Alpha
Classifier: Intended Audience :: Developers
Classifier: License :: OSI Approved :: MIT License
Classifier: Programming Language :: Python :: 3
Classifier: Programming Language :: Python :: 3.7
Classifier: Programming Language :: Python :: 3.8
Classifier: Programming Language :: Python :: 3.9
Classifier: Programming Language :: Python :: 3.10
Classifier: Programming Language :: Python :: 3.11
Classifier: Programming Language :: Python :: 3.12
Classifier: Programming Language :: Python :: 3.13
Requires-Dist: opentelemetry-api
Requires-Dist: opentelemetry-sdk
Requires-Dist: opentelemetry-exporter-otlp
Requires-Dist: requests
Requires-Dist: huaweicloudsdkcore
Requires-Dist: huaweicloudsdknlp
Requires-Dist: esdk-obs-python
